abq/__init__.py
abq/async_retry.py
abq/bq.py
abq/job.py
abq/rows_parser.py
abq-0.1.5.dist-info/WHEEL
abq-0.1.5.dist-info/METADATA
abq-0.1.5.dist-info/RECORD
