Metadata-Version: 2.1
Name: abq
Version: 0.1.5
Summary: 
Author: sakuv2
Author-email: loots2438@gmail.com
Requires-Python: >=3.7,<4.0
Classifier: Programming Language :: Python :: 3
Classifier: Programming Language :: Python :: 3.7
Classifier: Programming Language :: Python :: 3.8
Classifier: Programming Language :: Python :: 3.9
Requires-Dist: google-cloud-bigquery (>=1.25.0,<2.0.0)
Requires-Dist: httpx (>=0.16.1,<0.17.0)
Requires-Dist: oauth2client (>=4.1.3,<5.0.0)
Requires-Dist: pydantic[dotenv] (>=1.5.1,<2.0.0)
